{
    "variants": {
        "facing=north": {
            "model": "stewblocks:furniture_garden_wooden_table",
            "y": 270
        },
        "facing=south": {
            "model": "stewblocks:furniture_garden_wooden_table",
            "y": 90
        },
        "facing=west": {
            "model": "stewblocks:furniture_garden_wooden_table",
            "y": 180
        },
        "facing=east": {
            "model": "stewblocks:furniture_garden_wooden_table",
            "y": 0
        }
    }
}
